learn_python_ceg_test/__init__.py
learn_python_ceg_test/check_answers.py
learn_python_ceg_test-1.0.2.dist-info/LICENSE.txt
learn_python_ceg_test-1.0.2.dist-info/METADATA
learn_python_ceg_test-1.0.2.dist-info/WHEEL
learn_python_ceg_test-1.0.2.dist-info/top_level.txt
learn_python_ceg_test-1.0.2.dist-info/RECORD
